{
    "id": 17,
    "topic": "Cybersecurity",
    "heading": "Understanding Malware Types",
    "author": "Alex Ray",
    "date": "2025-08-31",
    "content": "<p>Malware, short for malicious software, comes in many forms. Viruses attach themselves to clean files, worms spread across networks, trojans disguise themselves as legitimate software, and ransomware encrypts your files and demands a payment.</p><p>Understanding the different types is the first step in protecting yourself from them.</p>"
}